triangle/__init__.py
triangle/core.cpython-313-aarch64-linux-gnu.so
triangle/data.py
triangle/plot.py
triangle/tri.py
triangle/version.py
triangle/data/A.1.ele
triangle/data/A.1.node
triangle/data/A.1.poly
triangle/data/A.poly
triangle/data/bbox.1.area
triangle/data/bbox.1.ele
triangle/data/bbox.1.node
triangle/data/box.1.ele
triangle/data/box.1.node
triangle/data/box.1.poly
triangle/data/box.2.ele
triangle/data/box.2.node
triangle/data/box.2.poly
triangle/data/box.3.ele
triangle/data/box.3.node
triangle/data/box.3.poly
triangle/data/box.4.ele
triangle/data/box.4.node
triangle/data/box.4.poly
triangle/data/box.poly
triangle/data/diamond_02_00009.1.ele
triangle/data/diamond_02_00009.1.node
triangle/data/diamond_02_00009.1.v.edge
triangle/data/diamond_02_00009.1.v.node
triangle/data/diamond_02_00009.node
triangle/data/dots.1.v.edge
triangle/data/dots.1.v.node
triangle/data/dots.node
triangle/data/double_hex.1.ele
triangle/data/double_hex.1.node
triangle/data/double_hex.1.poly
triangle/data/double_hex.2.ele
triangle/data/double_hex.2.node
triangle/data/double_hex.2.poly
triangle/data/double_hex.poly
triangle/data/double_hex2.1.ele
triangle/data/double_hex2.1.node
triangle/data/double_hex2.1.poly
triangle/data/double_hex2.2.ele
triangle/data/double_hex2.2.node
triangle/data/double_hex2.2.poly
triangle/data/double_hex2.poly
triangle/data/double_hex3.1.ele
triangle/data/double_hex3.1.node
triangle/data/double_hex3.1.poly
triangle/data/double_hex3.node
triangle/data/double_hex3.poly
triangle/data/ell.ele
triangle/data/ell.node
triangle/data/face.1.ele
triangle/data/face.1.node
triangle/data/face.1.poly
triangle/data/face.poly
triangle/data/greenland.ele
triangle/data/greenland.node
triangle/data/la.1.ele
triangle/data/la.1.node
triangle/data/la.1.poly
triangle/data/la.poly
triangle/data/spiral.1.ele
triangle/data/spiral.1.node
triangle/data/spiral.node
triangle/data/spiral.q.1.ele
triangle3-20250811.1.dist-info/METADATA
triangle3-20250811.1.dist-info/WHEEL
triangle3-20250811.1.dist-info/top_level.txt
triangle3-20250811.1.dist-info/RECORD
triangle3-20250811.1.dist-info/licenses/LICENSE
