Metadata-Version: 2.1
Name: triangle3
Version: 20250811.1
Summary: Python binding to the triangle library
Author-email: Dzhelil Rufat <d@rufat.be>
License: LGPL-3.0
Project-URL: Homepage, https://rufat.be/triangle
Project-URL: Repository, https://github.com/drufat/triangle
Requires-Python: >=3.7
License-File: LICENSE
Requires-Dist: numpy
Provides-Extra: test
Requires-Dist: pytest ; extra == 'test'
